lab_helper/__init__.py
lab_helper/pandas_utils.py
lab_helper/stats.py
lab_helper/symbolic.py
labhelper/__init__.py
labhelper/graphing.py
labhelper/pandas_utils.py
labhelper/stats.py
labhelper/sym.py
labhelper/symbolic.py
labhelper/sympy_enclosure.py
labhelper/test.py
labhelper/units.py
labhelper/unit_systems/CGS.py
labhelper/unit_systems/SI.py
labhelper/unit_systems/__init__.py
labhelper/unit_systems/prefixes.py
labhelper-0.1.0.dist-info/METADATA
labhelper-0.1.0.dist-info/WHEEL
labhelper-0.1.0.dist-info/top_level.txt
labhelper-0.1.0.dist-info/RECORD
