Metadata-Version: 2.1
Name: labhelper
Version: 0.1.0
Summary: A basic package with handy function for lab work, made for Jupyter Notebooks
Author: Batres (Javier Batres)
Author-email: <javibatresdc@gmail.com>
Keywords: python,data analysis,lab,data,symbolic
Classifier: Development Status :: 1 - Planning
Classifier: Intended Audience :: Science/Research
Classifier: Programming Language :: Python :: 3.5
Classifier: Framework :: Jupyter
Classifier: Operating System :: Unix
Classifier: Operating System :: MacOS :: MacOS X
Classifier: Operating System :: Microsoft :: Windows
Requires-Python: >=3.5
Requires-Dist: scipy
Requires-Dist: pandas
Requires-Dist: numpy
Requires-Dist: sympy
Requires-Dist: IPython
Requires-Dist: pyperclip
Requires-Dist: Jinja2
Requires-Dist: seaborn
